fluentcms_teaser/__init__.py
fluentcms_teaser/appsettings.py
fluentcms_teaser/content_plugins.py
fluentcms_teaser/models.py
fluentcms_teaser/tests.py
fluentcms_teaser/locale/nl/LC_MESSAGES/django.mo
fluentcms_teaser/locale/nl/LC_MESSAGES/django.po
fluentcms_teaser/locale/ru/LC_MESSAGES/django.mo
fluentcms_teaser/locale/ru/LC_MESSAGES/django.po
fluentcms_teaser/migrations/0001_initial.py
fluentcms_teaser/migrations/0002_auto_20150903_0711.py
fluentcms_teaser/migrations/0003_teaseritem_url_title.py
fluentcms_teaser/migrations/__init__.py
fluentcms_teaser/templates/admin/fluentcms_teaser/admin_init.html
fluentcms_teaser/templates/fluentcms_teaser/teaser.html
fluentcms_teaser-2.0.dist-info/AUTHORS
fluentcms_teaser-2.0.dist-info/LICENSE
fluentcms_teaser-2.0.dist-info/METADATA
fluentcms_teaser-2.0.dist-info/WHEEL
fluentcms_teaser-2.0.dist-info/top_level.txt
fluentcms_teaser-2.0.dist-info/RECORD
